antistasi_sqf_tools/__init__.py
antistasi_sqf_tools/__main__.py
antistasi_sqf_tools/errors.py
antistasi_sqf_tools/utilities.py
antistasi_sqf_tools/config_creation/__init__.py
antistasi_sqf_tools/config_creation/config_classes.py
antistasi_sqf_tools/config_creation/config_writer.py
antistasi_sqf_tools/doc_creating/__init__.py
antistasi_sqf_tools/doc_creating/config_handling.py
antistasi_sqf_tools/doc_creating/creator.py
antistasi_sqf_tools/doc_creating/env_handling.py
antistasi_sqf_tools/doc_creating/isolated_build_env.py
antistasi_sqf_tools/doc_creating/preprocessing/__init__.py
antistasi_sqf_tools/doc_creating/preprocessing/preprocessor.py
antistasi_sqf_tools/doc_creating/setup/__init__.py
antistasi_sqf_tools/doc_creating/setup/file_creator.py
antistasi_sqf_tools/doc_creating/setup/setup_docs.py
antistasi_sqf_tools/doc_creating/setup/templates/__init__.py
antistasi_sqf_tools/doc_creating/setup/templates/conf.jinja_py
antistasi_sqf_tools/doc_creating/setup/templates/default_generate_config.ini
antistasi_sqf_tools/doc_creating/setup/templates/glossary.jinja_rst
antistasi_sqf_tools/doc_creating/setup/templates/index.jinja_rst
antistasi_sqf_tools/doc_creating/setup/templates/placeholder_favicon.png
antistasi_sqf_tools/doc_creating/setup/templates/placeholder_logo.png
antistasi_sqf_tools/doc_creating/sphinx_extensions/__init__.py
antistasi_sqf_tools/doc_creating/sphinx_extensions/include_external/__init__.py
antistasi_sqf_tools/doc_creating/sphinx_extensions/links_collection/__init__.py
antistasi_sqf_tools/doc_creating/sphinx_extensions/links_collection/external_link.py
antistasi_sqf_tools/doc_creating/sphinx_extensions/links_collection/external_link_collection.py
antistasi_sqf_tools/doc_creating/sphinx_extensions/links_collection/external_links_style.css
antistasi_sqf_tools/doc_creating/sphinx_extensions/links_collection/link_file_creation.py
antistasi_sqf_tools/doc_creating/sphinx_extensions/misc_additions/__init__.py
antistasi_sqf_tools-0.6.0.dist-info/entry_points.txt
antistasi_sqf_tools-0.6.0.dist-info/LICENSE
antistasi_sqf_tools-0.6.0.dist-info/WHEEL
antistasi_sqf_tools-0.6.0.dist-info/METADATA
antistasi_sqf_tools-0.6.0.dist-info/RECORD
