Metadata-Version: 2.1
Name: antistasi_sqf_tools
Version: 0.6.0
Summary: WIP
Author: antistasi_tools
Requires-Python: >=3.10
Classifier: License :: OSI Approved :: MIT License
Requires-Dist: click>=8.1
Requires-Dist: pygithub>=1.55
Requires-Dist: pyparsing>=3.0
Requires-Dist: python-dotenv>=0.20
Requires-Dist: rich>=12.6.0
Requires-Dist: sphinx>=5.3.0
Requires-Dist: yarl>=1.8
Project-URL: Source, https://github.com/Giddius/Antistasi_Logbook
